phcnb/__init__.py
phcnb/__main__.py
phcnb/cli.py
phcnb-0.1.2.dist-info/entry_points.txt
phcnb-0.1.2.dist-info/WHEEL
phcnb-0.1.2.dist-info/METADATA
phcnb-0.1.2.dist-info/RECORD
